[
  {
    "boss_name": "Autonomous Assault Unit - Typhon Destroyer",
    "timeline": [
      {
        "date": "2025-01-10",
        "hp": 58889396,
        "boss_id": 69002
      },
      {
        "date": "2025-02-07",
        "hp": 64522295,
        "boss_id": 69004
      },
      {
        "date": "2025-03-21",
        "hp": 79372665,
        "boss_id": 69007
      },
      {
        "date": "2025-04-04",
        "hp": 79372665,
        "boss_id": 69008
      },
      {
        "date": "2025-05-16",
        "hp": 82445155,
        "boss_id": 69011
      },
      {
        "date": "2025-08-22",
        "hp": 89614299,
        "boss_id": 69018
      },
      {
        "date": "2025-11-14",
        "hp": 112657976,
        "boss_id": 69024
      }
    ]
  },
  {
    "boss_name": "Corrupted Overlord - Pompey",
    "timeline": [
      {
        "date": "2024-12-20",
        "hp": 58395085,
        "boss_id": 69001
      },
      {
        "date": "2025-01-24",
        "hp": 70074102,
        "boss_id": 69003
      },
      {
        "date": "2025-03-21",
        "hp": 78608768,
        "boss_id": 69007
      },
      {
        "date": "2025-05-02",
        "hp": 78608768,
        "boss_id": 69010
      },
      {
        "date": "2025-07-11",
        "hp": 83100698,
        "boss_id": 69015
      }
    ]
  },
  {
    "boss_name": "Dead End Butcher",
    "timeline": [
      {
        "date": "2025-01-10",
        "hp": 59700536,
        "boss_id": 69002
      },
      {
        "date": "2025-02-21",
        "hp": 71640643,
        "boss_id": 69005
      },
      {
        "date": "2025-04-18",
        "hp": 65297461,
        "boss_id": 69009
      }
    ]
  },
  {
    "boss_name": "Miasma Priest",
    "timeline": [
      {
        "date": "2025-06-13",
        "hp": 77665112,
        "boss_id": 69013
      },
      {
        "date": "2025-07-11",
        "hp": 77665112,
        "boss_id": 69015
      },
      {
        "date": "2025-07-25",
        "hp": 91370720,
        "boss_id": 69016
      },
      {
        "date": "2025-08-22",
        "hp": 91370720,
        "boss_id": 69018
      },
      {
        "date": "2025-09-05",
        "hp": 109644864,
        "boss_id": 69019
      },
      {
        "date": "2025-10-03",
        "hp": 109644864,
        "boss_id": 69021
      },
      {
        "date": "2025-10-17",
        "hp": 114213400,
        "boss_id": 69022
      },
      {
        "date": "2025-11-14",
        "hp": 114213400,
        "boss_id": 69024
      },
      {
        "date": "2026-01-09",
        "hp": 127919008,
        "boss_id": 69028
      }
    ]
  },
  {
    "boss_name": "Miasmic Fiend - Unfathomable",
    "timeline": [
      {
        "date": "2025-07-25",
        "hp": 101800565,
        "boss_id": 69016
      },
      {
        "date": "2025-08-08",
        "hp": 101800565,
        "boss_id": 69017
      },
      {
        "date": "2025-09-05",
        "hp": 121503901,
        "boss_id": 69019
      },
      {
        "date": "2025-10-03",
        "hp": 121503901,
        "boss_id": 69021
      },
      {
        "date": "2025-10-31",
        "hp": 134639458,
        "boss_id": 69023
      },
      {
        "date": "2025-11-28",
        "hp": 160910571,
        "boss_id": 69025
      },
      {
        "date": "2025-12-26",
        "hp": 154342793,
        "boss_id": 69027
      }
    ]
  },
  {
    "boss_name": "Notorious - Dead End Butcher",
    "timeline": [
      {
        "date": "2025-01-24",
        "hp": 85970436,
        "boss_id": 69003
      },
      {
        "date": "2025-02-07",
        "hp": 85970436,
        "boss_id": 69004
      },
      {
        "date": "2025-05-16",
        "hp": 102985418,
        "boss_id": 69011
      },
      {
        "date": "2025-07-11",
        "hp": 107463045,
        "boss_id": 69015
      },
      {
        "date": "2025-08-08",
        "hp": 118657112,
        "boss_id": 69017
      },
      {
        "date": "2025-08-22",
        "hp": 118657112,
        "boss_id": 69018
      },
      {
        "date": "2025-09-19",
        "hp": 134328806,
        "boss_id": 69020
      },
      {
        "date": "2025-10-17",
        "hp": 136567620,
        "boss_id": 69022
      }
    ]
  },
  {
    "boss_name": "Notorious - Marionette",
    "timeline": [
      {
        "date": "2024-12-20",
        "hp": 58049652,
        "boss_id": 69001
      },
      {
        "date": "2025-02-07",
        "hp": 69659582,
        "boss_id": 69004
      },
      {
        "date": "2025-04-04",
        "hp": 78367030,
        "boss_id": 69008
      },
      {
        "date": "2025-05-16",
        "hp": 84171995,
        "boss_id": 69011
      },
      {
        "date": "2025-05-30",
        "hp": 84171995,
        "boss_id": 69012
      },
      {
        "date": "2025-06-13",
        "hp": 89976961,
        "boss_id": 69013
      },
      {
        "date": "2025-08-08",
        "hp": 98684408,
        "boss_id": 69017
      },
      {
        "date": "2025-11-28",
        "hp": 127709235,
        "boss_id": 69025
      },
      {
        "date": "2026-01-09",
        "hp": 139319165,
        "boss_id": 69028
      }
    ]
  },
  {
    "boss_name": "Notorious - Pompey",
    "timeline": [
      {
        "date": "2025-02-21",
        "hp": 70074102,
        "boss_id": 69005
      },
      {
        "date": "2025-03-07",
        "hp": 77261189,
        "boss_id": 69006
      },
      {
        "date": "2025-04-04",
        "hp": 78608768,
        "boss_id": 69008
      },
      {
        "date": "2025-05-30",
        "hp": 84672873,
        "boss_id": 69012
      },
      {
        "date": "2025-06-13",
        "hp": 83100698,
        "boss_id": 69013
      },
      {
        "date": "2025-06-27",
        "hp": 83100698,
        "boss_id": 69014
      },
      {
        "date": "2025-07-25",
        "hp": 89838592,
        "boss_id": 69016
      },
      {
        "date": "2025-09-19",
        "hp": 102415995,
        "boss_id": 69020
      }
    ]
  },
  {
    "boss_name": "Sacrifice - Bringer",
    "timeline": [
      {
        "date": "2024-12-20",
        "hp": 76362803,
        "boss_id": 69001
      },
      {
        "date": "2025-01-10",
        "hp": 76362803,
        "boss_id": 69002
      },
      {
        "date": "2025-02-21",
        "hp": 89838592,
        "boss_id": 69005
      },
      {
        "date": "2025-03-07",
        "hp": 89838592,
        "boss_id": 69006
      },
      {
        "date": "2025-04-18",
        "hp": 103314381,
        "boss_id": 69009
      },
      {
        "date": "2025-05-02",
        "hp": 110501469,
        "boss_id": 69010
      },
      {
        "date": "2025-05-30",
        "hp": 110501469,
        "boss_id": 69012
      },
      {
        "date": "2025-06-27",
        "hp": 114544205,
        "boss_id": 69014
      },
      {
        "date": "2025-12-12",
        "hp": 170693326,
        "boss_id": 69026
      }
    ]
  },
  {
    "boss_name": "The Defiler",
    "timeline": [
      {
        "date": "2025-09-05",
        "hp": 99020956,
        "boss_id": 69019
      },
      {
        "date": "2025-09-19",
        "hp": 99020956,
        "boss_id": 69020
      },
      {
        "date": "2025-10-17",
        "hp": 109630345,
        "boss_id": 69022
      },
      {
        "date": "2025-10-31",
        "hp": 109630345,
        "boss_id": 69023
      }
    ]
  },
  {
    "boss_name": "Unknown Corruption Complex",
    "timeline": [
      {
        "date": "2025-01-24",
        "hp": 75669077,
        "boss_id": 69003
      },
      {
        "date": "2025-03-07",
        "hp": 75669077,
        "boss_id": 69006
      },
      {
        "date": "2025-03-21",
        "hp": 75669077,
        "boss_id": 69007
      },
      {
        "date": "2025-04-18",
        "hp": 75669077,
        "boss_id": 69009
      },
      {
        "date": "2025-05-02",
        "hp": 84885182,
        "boss_id": 69010
      },
      {
        "date": "2025-06-27",
        "hp": 89735764,
        "boss_id": 69014
      },
      {
        "date": "2025-10-03",
        "hp": 116413965,
        "boss_id": 69021
      },
      {
        "date": "2026-01-23",
        "hp": 130965710,
        "boss_id": 69029
      }
    ]
  },
  {
    "boss_name": "Wandering Hunter",
    "timeline": [
      {
        "date": "2025-10-31",
        "hp": 120421465,
        "boss_id": 69023
      },
      {
        "date": "2025-11-14",
        "hp": 120421465,
        "boss_id": 69024
      },
      {
        "date": "2025-12-12",
        "hp": 137873851,
        "boss_id": 69026
      },
      {
        "date": "2025-12-26",
        "hp": 152708379,
        "boss_id": 69027
      },
      {
        "date": "2026-01-23",
        "hp": 152708379,
        "boss_id": 69029
      }
    ]
  },
  {
    "boss_name": "Ye Shiyuan the Thrall",
    "timeline": [
      {
        "date": "2025-11-28",
        "hp": 161506628,
        "boss_id": 69025
      },
      {
        "date": "2025-12-12",
        "hp": 161506628,
        "boss_id": 69026
      },
      {
        "date": "2026-01-09",
        "hp": 161506628,
        "boss_id": 69028
      }
    ]
  },
  {
    "boss_name": "太初梦魇",
    "timeline": [
      {
        "date": "2025-12-26",
        "hp": 126875774,
        "boss_id": 69027
      },
      {
        "date": "2026-01-23",
        "hp": 126875774,
        "boss_id": 69029
      }
    ]
  }
]